basicsynbio/__init__.py
basicsynbio/bsb_io.py
basicsynbio/decorators.py
basicsynbio/main.py
basicsynbio/cam/__init__.py
basicsynbio/cam/csv_export.py
basicsynbio/cam/default_linker_plate.py
basicsynbio/cam/echo_instructions.py
basicsynbio/cam/main.py
basicsynbio/cam/misc_funs.py
basicsynbio/cam/pdf_instructions.py
basicsynbio/parts_linkers/BASIC_CDS_collection_v01.gb
basicsynbio/parts_linkers/BASIC_CDS_collection_v02.gb
basicsynbio/parts_linkers/BASIC_SEVA_66-11_&_69-11.gb
basicsynbio/parts_linkers/BASIC_SEVA_collection_v01.gb
basicsynbio/parts_linkers/BASIC_SEVA_collection_v10.gb
basicsynbio/parts_linkers/BASIC_promoter_collection_v01.gb
basicsynbio/parts_linkers/BASIC_promoter_collection_v02.gb
basicsynbio/parts_linkers/BASIC_promoter_collection_v03.gb
basicsynbio/parts_linkers/__init__.py
basicsynbio/parts_linkers/basic_parts.py
basicsynbio/parts_linkers/biolegio_linkers.py
basicsynbio/parts_linkers/main.py
basicsynbio/static/__init__.py
basicsynbio/static/introimg.png
basicsynbio/utils/__init__.py
basicsynbio/utils/benchling.py
basicsynbio/utils/biopython.py
basicsynbio/utils/primer3py.py
basicsynbio/utils/reportLab.py
basicsynbio/utils/seva.py
tests/__init__.py
tests/conftest.py
tests/functions.py
tests/test_bsbio.py
tests/test_cam.py
tests/test_decorators.py
tests/test_echo_clips.py
tests/test_fixtures.py
tests/test_function_echo.py
tests/test_function_pdf.py
tests/test_main.py
tests/test_parts_linkers.py
basicsynbio-0.8.0.dist-info/LICENSE
basicsynbio-0.8.0.dist-info/METADATA
basicsynbio-0.8.0.dist-info/WHEEL
basicsynbio-0.8.0.dist-info/top_level.txt
basicsynbio-0.8.0.dist-info/RECORD
