Metadata-Version: 2.1
Name: basicsynbio
Version: 0.8.0
Summary: An open-source Python package to facilitate BASIC DNA Assembly workflows
Home-page: https://github.com/LondonBiofoundry/basicsynbio
Author: LondonBiofoundry
Author-email: hainesm6@gmail.com
License: BSD-3-Clause License
Project-URL: Documentation, https://londonbiofoundry.github.io/basicsynbio/index.html
Project-URL: Source, https://github.com/LondonBiofoundry/basicsynbio
Platform: UNKNOWN
Classifier: Intended Audience :: Science/Research
Classifier: License :: OSI Approved :: BSD License
Classifier: Natural Language :: English
Classifier: Operating System :: OS Independent
Classifier: Programming Language :: Python :: 3.8
Classifier: Topic :: Scientific/Engineering :: Bio-Informatics
Requires-Python: >=3.8
License-File: LICENSE
Requires-Dist: biopython (>=1.78)
Requires-Dist: pandas
Requires-Dist: platemap
Requires-Dist: primer3-py
Requires-Dist: python-Levenshtein
Requires-Dist: reportlab
Requires-Dist: sbol2
